dane/__init__.py
dane/base_classes.py
dane/config.py
dane/document.py
dane/errors.py
dane/es_queries.py
dane/handlers/ESHandler.py
dane/handlers/RabbitMQHandler.py
dane/handlers/__init__.py
dane/handlers/base_handler.py
dane/provenance.py
dane/results.py
dane/s3_util.py
dane/state.py
dane/tasks.py
dane/utils.py
dane-0.4.3.dist-info/LICENSE
dane-0.4.3.dist-info/METADATA
dane-0.4.3.dist-info/WHEEL
dane-0.4.3.dist-info/RECORD
