Metadata-Version: 2.1
Name: DANE
Version: 0.4.3
Summary: Utils for working with the Distributed Annotation and Enrichment system
Home-page: https://github.com/CLARIAH/DANE
License: Apache-2.0
Author: Nanne van Noord
Author-email: n.j.e.vannoord@uva.nl
Requires-Python: >=3.10,<4.0
Classifier: Development Status :: 4 - Beta
Classifier: Intended Audience :: Developers
Classifier: Intended Audience :: Science/Research
Classifier: License :: OSI Approved :: Apache Software License
Classifier: Programming Language :: Python :: 3
Classifier: Programming Language :: Python :: 3.10
Classifier: Programming Language :: Python :: 3.11
Classifier: Programming Language :: Python :: 3.12
Classifier: Topic :: Multimedia :: Video
Classifier: Topic :: Scientific/Engineering :: Artificial Intelligence
Classifier: Topic :: Software Development :: Libraries :: Python Modules
Requires-Dist: boto3 (>=1.26.155,<2.0.0)
Requires-Dist: elasticsearch7 (>=7.17.7,<8.0.0)
Requires-Dist: pika (>=1.3.1,<2.0.0)
Requires-Dist: requests (>=2.28.1,<3.0.0)
Requires-Dist: urllib3 (>=1.26.12,<2.0.0)
Requires-Dist: yacs (>=0.1.8,<0.2.0)
Project-URL: Repository, https://github.com/CLARIAH/DANE
